LICENSE
README.md
setup.cfg
setup.py
smapi/__init__.py
smapi/smapi.py
smapi.egg-info/PKG-INFO
smapi.egg-info/SOURCES.txt
smapi.egg-info/dependency_links.txt
smapi.egg-info/not-zip-safe
smapi.egg-info/requires.txt
smapi.egg-info/top_level.txt
smapi/data_handlers/__init__.py
smapi/data_handlers/data_fetcher.py
smapi/data_handlers/data_parser.py
smapi/errors/__init__.py
smapi/errors/connection_errors.py
smapi/errors/runtime_errors.py
smapi/info/__init__.py
smapi/info/info.py
smapi/info/locales.py