Metadata-Version: 2.1
Name: smapi
Version: 0.1.4
Summary: Fetching and parsing info from Steam Community Market and CSGO Float Apis
Home-page: https://github.com/Mefgner/SteamMarketAPI
Author: Mefgner
Author-email: mefgner@gmail.com
License: MIT
Keywords: smapi,steam,community,market,csgo,cs:go,listings,float,api
Platform: UNKNOWN
Requires-Python: ~=3.7
License-File: LICENSE
